README.md
setup.py
remarkable_sim/__init__.py
remarkable_sim/evsim.py
remarkable_sim/sim.py
rmkit_sim.egg-info/PKG-INFO
rmkit_sim.egg-info/SOURCES.txt
rmkit_sim.egg-info/dependency_links.txt
rmkit_sim.egg-info/entry_points.txt
rmkit_sim.egg-info/requires.txt
rmkit_sim.egg-info/top_level.txt