Metadata-Version: 2.1
Name: rmkit-sim
Version: 0.0.2
Summary: fork of remarkable-sim
Home-page: https://github.com/rmkit-dev/remarkable_sim
Author: rmkit-dev
Author-email: 
License: GPLv3
Keywords: remarkable evdev sim simulator simulation tablet
Platform: UNKNOWN
Classifier: Programming Language :: Python :: 3
